parsit/__init__.py
parsit/pdf_parse_union_core_v2.py
parsit/chunking/__init__.py
parsit/chunking/chunker.py
parsit/chunking/process.py
parsit/config/__init__.py
parsit/config/constants.py
parsit/config/drop_reason.py
parsit/config/drop_tag.py
parsit/config/enums.py
parsit/config/exceptions.py
parsit/config/make_content_config.py
parsit/config/model_block_type.py
parsit/config/ocr_content_type.py
parsit/config/signature_config.py
parsit/data/__init__.py
parsit/data/batch_build_dataset.py
parsit/data/dataset.py
parsit/data/read_api.py
parsit/data/schemas.py
parsit/data/utils.py
parsit/data/data_reader_writer/__init__.py
parsit/data/data_reader_writer/base.py
parsit/data/data_reader_writer/filebase.py
parsit/data/data_reader_writer/multi_bucket_s3.py
parsit/data/data_reader_writer/s3.py
parsit/data/io/__init__.py
parsit/data/io/base.py
parsit/data/io/http.py
parsit/data/io/s3.py
parsit/dict2md/__init__.py
parsit/dict2md/ocr_mkcontent.py
parsit/filter/__init__.py
parsit/filter/document_classifier.py
parsit/filter/pdf_classify_by_type.py
parsit/filter/pdf_meta_scan.py
parsit/integrations/__init__.py
parsit/integrations/rag/__init__.py
parsit/integrations/rag/api.py
parsit/integrations/rag/type.py
parsit/integrations/rag/utils.py
parsit/libs/__init__.py
parsit/libs/boxbase.py
parsit/libs/clean_memory.py
parsit/libs/commons.py
parsit/libs/config_reader.py
parsit/libs/convert_utils.py
parsit/libs/coordinate_transform.py
parsit/libs/draw_bbox.py
parsit/libs/hash_utils.py
parsit/libs/json_compressor.py
parsit/libs/language.py
parsit/libs/local_math.py
parsit/libs/markdown_utils.py
parsit/libs/path_utils.py
parsit/libs/pdf_check.py
parsit/libs/pdf_image_tools.py
parsit/libs/performance_stats.py
parsit/libs/safe_filename.py
parsit/libs/version.py
parsit/model/__init__.py
parsit/model/batch_analyze.py
parsit/model/doc_analyze_by_custom_model.py
parsit/model/magic_model.py
parsit/model/model_list.py
parsit/model/pdf_extract_kit.py
parsit/model/pp_structure_v2.py
parsit-0.1.1.dist-info/METADATA
parsit-0.1.1.dist-info/WHEEL
parsit-0.1.1.dist-info/entry_points.txt
parsit-0.1.1.dist-info/top_level.txt
parsit-0.1.1.dist-info/RECORD
